[{"name":"Deorren","teamname":"Golden State","reason":"Back to back champions!","id":34},{"name":"lcanchan","teamname":"Celtics","reason":"I dont know","id":80},{"name":"Joshue","teamname":"Hawks","reason":"Trey Young","id":64},{"name":"sucanchan89@gmail.com","teamname":"Celtics","reason":"GOAT","id":84},{"name":"joshua","teamname":"Lakers","reason":"Because of Lebron James","id":70},{"name":"asd","teamname":"Cleveland Cavaliers","reason":"Young teams","id":70},{"name":"anonymous","teamname":"Golden State Warriors","reason":"Better team","id":71},{"name":"Test","teamname":"Golden State Warriors","reason":"They are going back to back","id":96},{"name":"lcanchan","teamname":"Detroit Pistons","reason":"Young Team","id":37},{"name":"Deorren","teamname":"Brooklyn Nets","reason":"Durant, Kyrie","id":29},{"name":"Deorren","teamname":"Brooklyn Nets","reason":"Durant, Kyrie","id":22},{"name":"sucanchan89@gmail.com","teamname":"Brooklyn Nets","reason":"Young Team","id":87},{"name":"sucanchan89@gmail.com","teamname":"Brooklyn Nets","reason":"Young Team","id":88},{"name":"Deorren","teamname":"Denver Nuggets","reason":"GOAT","id":58},{"name":"lcanchan","teamname":"Los Angeles Lakers","reason":"GOAT","id":81},{"name":"sucanchan89@gmail.com","teamname":"Boston Celtics","reason":"Young Team","id":19},{"name":"UTHRED","teamname":"Chicago Bulls","reason":"Michael jordan","id":82},{"name":"sucanchan89@gmail.com","teamname":"Atlanta Hawks","reason":"I dont know","id":44},{"name":"BRADNE CANCHAN","teamname":"New York Knicks","reason":"I LIKLE THE COLD","id":85},{"name":"KATIE","teamname":"Milwaukee Bucks","reason":"GIANNIS","id":98},{"name":"COLOMBIA","teamname":"Atlanta Hawks","reason":"16 RUNNER UP","id":46},{"name":"JOSHYUA DANIUEL","teamname":"Atlanta Hawks","reason":"TREYY YOUNGGG","id":3},{"name":"JACOB KENJI","teamname":"New York Knicks","reason":"SPIKE LEE","id":90}]